scrapely-0.12.0.dist-info/RECORD
scrapely-0.12.0.dist-info/WHEEL
scrapely-0.12.0.dist-info/metadata.json
scrapely-0.12.0.dist-info/DESCRIPTION.rst
scrapely-0.12.0.dist-info/METADATA
scrapely-0.12.0.dist-info/top_level.txt
scrapely/tool.py
scrapely/template.py
scrapely/htmlpage.py
scrapely/extractors.py
scrapely/descriptor.py
scrapely/__init__.py
scrapely/extraction/similarity.py
scrapely/extraction/regionextract.py
scrapely/extraction/pageparsing.py
scrapely/extraction/pageobjects.py
scrapely/extraction/__init__.py
