Metadata-Version: 2.0
Name: scrapely
Version: 0.12.0
Summary: A pure-python HTML screen-scraping library
Home-page: http://github.com/scrapy/scrapely
Author: Scrapy project
Author-email: info@scrapy.org
License: BSD
Platform: UNKNOWN
Classifier: Development Status :: 5 - Production/Stable
Classifier: License :: OSI Approved :: BSD License
Classifier: Operating System :: OS Independent
Classifier: Programming Language :: Python
Classifier: Programming Language :: Python :: 2.6
Classifier: Programming Language :: Python :: 2.7
Classifier: Topic :: Internet :: WWW/HTTP
Classifier: Topic :: Text Processing :: Markup :: HTML
Requires-Dist: numpy
Requires-Dist: w3lib
